ethereal/__init__.py
ethereal/async_rest_client.py
ethereal/async_ws_client.py
ethereal/base_client.py
ethereal/chain_client.py
ethereal/constants.py
ethereal/py.typed
ethereal/rest_client.py
ethereal/rest_client.pyi
ethereal/ws_client.py
ethereal/contracts/13374201/ExchangeGateway.json
ethereal/contracts/13374202/ExchangeGateway.json
ethereal/contracts/31337/ExchangeGateway.json
ethereal/contracts/5064014/ExchangeGateway.json
ethereal/contracts/common/ERC20.json
ethereal/contracts/common/WUSDe.json
ethereal/models/__init__.py
ethereal/models/config.py
ethereal/models/rest.py
ethereal/models/devnet/rest.py
ethereal/models/mainnet/rest.py
ethereal/models/testnet/rest.py
ethereal/rest/__init__.py
ethereal/rest/async_http_client.py
ethereal/rest/funding.py
ethereal/rest/http_client.py
ethereal/rest/linked_signer.py
ethereal/rest/order.py
ethereal/rest/position.py
ethereal/rest/product.py
ethereal/rest/referral.py
ethereal/rest/rpc.py
ethereal/rest/subaccount.py
ethereal/rest/token.py
ethereal/rest/util.py
ethereal/ws/__init__.py
ethereal/ws/async_ws_base.py
ethereal/ws/ws_base.py
examples/cli.py
scripts/check_test_account.py
scripts/generate_docstrings.py
scripts/generate_sync_client.py
scripts/generate_types.py
scripts/setup_test_account.py
tests/__init__.py
tests/conftest.py
tests/helpers.py
tests/test_async_clients.py
tests/test_chain.py
tests/test_clients.py
tests/test_signing.py
tests/test_util.py
tests/rest/async/test_async_rest_info.py
tests/rest/async/test_async_rest_info_account.py
tests/rest/async/test_async_rest_orders.py
tests/rest/async/test_async_rest_orders_oto_oco.py
tests/rest/async/test_async_rest_position_liquidations.py
tests/rest/async/test_async_rest_signers.py
tests/rest/async/test_async_rest_subaccount_archive.py
tests/rest/async/test_async_rest_token.py
tests/rest/sync/test_sync_rest_info.py
tests/rest/sync/test_sync_rest_info_account.py
tests/rest/sync/test_sync_rest_orders.py
tests/rest/sync/test_sync_rest_orders_oto_oco.py
ethereal_sdk-0.1.0b23.dist-info/METADATA
ethereal_sdk-0.1.0b23.dist-info/WHEEL
ethereal_sdk-0.1.0b23.dist-info/top_level.txt
ethereal_sdk-0.1.0b23.dist-info/RECORD
