Metadata-Version: 2.4
Name: ethereal-sdk
Version: 0.1.0b23
Summary: Python SDK for interacting with the Ethereal API
Author: Meridian Labs
License: MIT
Project-URL: Homepage, https://github.com/meridianxyz/ethereal-py
Classifier: Intended Audience :: Developers
Classifier: Programming Language :: Python :: 3
Classifier: Programming Language :: Python :: 3.9
Classifier: Programming Language :: Python :: 3.10
Classifier: Programming Language :: Python :: 3.11
Classifier: Programming Language :: Python :: 3.12
Classifier: License :: OSI Approved :: MIT License
Classifier: Topic :: Software Development :: Libraries :: Python Modules
Requires-Python: >=3.9
Requires-Dist: eth-account>=0.13.5
Requires-Dist: pydantic>=2.11.2
Requires-Dist: python-dotenv>=1.0.1
Requires-Dist: python-socketio>=5.12.1
Requires-Dist: requests>=2.32.3
Requires-Dist: httpx>=0.27.0
Requires-Dist: web3>=7.9.0
Requires-Dist: uvloop>=0.21.0; sys_platform != "win32" and platform_python_implementation == "CPython"
